ra_fixture_generator/__init__.py
ra_fixture_generator/fixture_generator.py
ra_fixture_generator/generate_org_tree.py
ra_fixture_generator-0.2.0.dist-info/LICENSES/MPL-2.0.txt
ra_fixture_generator-0.2.0.dist-info/LICENSES/MIT.txt
ra_fixture_generator-0.2.0.dist-info/WHEEL
ra_fixture_generator-0.2.0.dist-info/METADATA
ra_fixture_generator-0.2.0.dist-info/RECORD
