Metadata-Version: 2.1
Name: ra-fixture-generator
Version: 0.2.0
Summary: Flatfile Fixture generator for OS2mo/LoRa
Home-page: https://magenta.dk/
License: MPL-2.0
Keywords: os2mo,lora
Author: Magenta
Author-email: info@magenta.dk
Requires-Python: >=3.8,<4.0
Classifier: License :: OSI Approved
Classifier: Programming Language :: Python :: 3
Classifier: Programming Language :: Python :: 3.8
Classifier: Programming Language :: Python :: 3.9
Requires-Dist: click (>=7.1.2,<8.0.0)
Requires-Dist: mimesis (>=4.1.3,<5.0.0)
Requires-Dist: pydantic (>=1.8.1,<2.0.0)
Requires-Dist: ra-flatfile-importer (>=0.1.2,<0.2.0)
Requires-Dist: ra-utils (>=0.4.0,<0.5.0)
Requires-Dist: ramodels (>=2.1.1,<3.0.0)
Project-URL: Repository, https://git.magenta.dk/rammearkitektur/ra-fixture-generator
